<?xml version="1.0" encoding="UTF-8"?>

<!-- generated on 2026-02-28 17:48:16 by Eclipse SUMO duarouter Version 1.24.0
<duarouterConfiguration xmlns:xsi="http://www.w3.org/2001/XMLSchema-instance" xsi:noNamespaceSchemaLocation="http://sumo.dlr.de/xsd/duarouterConfiguration.xsd">

    <input>
        <net-file value="./data/ntut_network_split.net copy.xml"/>
        <route-files value="./data/final_output.rou.alt.xml"/>
        <junction-taz value="true"/>
    </input>

    <output>
        <output-file value="./data/final_output.rou.xml"/>
        <alternatives-output value="./data/final_output.rou.alt.xml.tmp"/>
    </output>

    <processing>
        <max-alternatives value="3"/>
        <weights.random-factor value="12"/>
    </processing>

    <report>
        <ignore-errors value="true"/>
    </report>

</duarouterConfiguration>
-->

<routes xmlns:xsi="http://www.w3.org/2001/XMLSchema-instance" xsi:noNamespaceSchemaLocation="http://sumo.dlr.de/xsd/routes_file.xsd">
    <vType id="Car0" length="5.00" vClass="passenger" color="green"/>
    <vehicle id="Flow0.0" type="Car0" depart="0.00" fromTaz="cluster_3431431575_4777363357_655375231_6982059025" toTaz="3196998953">
        <routeDistribution last="2">
            <route cost="445.13" probability="0.33900874" edges="484988952#0 -51362430 1068440001 1239087513 593844221#0 1334904386#0 303647015#0"/>
            <route cost="279.76" probability="0.35883850" edges="484988952#0 -51362430 1068440001 1239087513 593844221#0 -594658757#2 303647015#0"/>
            <route cost="392.73" probability="0.30215275" edges="51362429#0 1068440006#0 1334904386#0 303647015#0"/>
        </routeDistribution>
    </vehicle>
    <vType id="Car1" length="5.00" vClass="passenger" color="green"/>
    <vehicle id="Flow1.0" type="Car1" depart="0.00" fromTaz="631668923" toTaz="622618112">
        <routeDistribution last="1">
            <route cost="358.04" probability="0.29818247" edges="1068234498#0 288135626#0 1068234499#0 -593847703#3 -593847705 593847704#0 49073272#0"/>
            <route cost="383.52" probability="0.36194119" edges="1068234498#0 288135626#0 1068234499#0 182334378#0 1068440004#1 593847702#0"/>
            <route cost="320.91" probability="0.33987635" edges="1068234498#0 288135626#0 1068234499#0 -593847703#3 593847702#0"/>
        </routeDistribution>
    </vehicle>
    <vType id="Car10" length="5.00" vClass="passenger" color="green"/>
    <vehicle id="Flow10.0" type="Car10" depart="0.00" fromTaz="cluster619136880_619136881_cluster_4510442270_5296993511_5296993513_619136931_#1more" toTaz="6252193077">
        <routeDistribution last="0">
            <route cost="162.89" probability="1.00000000" edges="196961377#0 196961377#3 593849718#0"/>
        </routeDistribution>
    </vehicle>
    <vType id="Car11" length="5.00" vClass="passenger" color="green"/>
    <vehicle id="Flow11.0" type="Car11" depart="0.00" fromTaz="cluster_9383263990_9383263991_9383263992_9383263993" toTaz="3139323041">
        <routeDistribution last="0">
            <route cost="76.73" probability="1.00000000" edges="506322841#1 198001764#0 182336887#2"/>
        </routeDistribution>
    </vehicle>
    <vType id="Car12" length="5.00" vClass="passenger" color="green"/>
    <vehicle id="Flow12.0" type="Car12" depart="0.00" fromTaz="cluster_9383263990_9383263991_9383263992_9383263993" toTaz="cluster_9383263990_9383263991_9383263992_9383263993">
        <routeDistribution last="0">
            <route cost="81.23" probability="1.00000000" edges="506322841#1 182336886 30620492#1"/>
        </routeDistribution>
    </vehicle>
    <vType id="Car13" length="5.00" vClass="passenger" color="green"/>
    <vehicle id="Flow13.0" type="Car13" depart="0.00" fromTaz="622618015" toTaz="622618230">
        <routeDistribution last="0">
            <route cost="32.27" probability="1.00000000" edges="49073274 593852346"/>
        </routeDistribution>
    </vehicle>
    <vType id="Car14" length="5.00" vClass="passenger" color="green"/>
    <vehicle id="Flow14.0" type="Car14" depart="0.00" fromTaz="3086736515" toTaz="622618144">
        <routeDistribution last="1">
            <route cost="56.42" probability="0.34822020" edges="-49073264#1 49073274"/>
            <route cost="26.91" probability="0.65177980" edges="593852343 906806086#0"/>
        </routeDistribution>
    </vehicle>
    <vType id="Car15" length="5.00" vClass="passenger" color="green"/>
    <vehicle id="Flow15.0" type="Car15" depart="0.00" fromTaz="cluster619136880_619136881_cluster_4510442270_5296993511_5296993513_619136931_#1more" toTaz="622618165">
        <routeDistribution last="0">
            <route cost="77.59" probability="1.00000000" edges="48794887#0"/>
        </routeDistribution>
    </vehicle>
    <vType id="Car16" length="5.00" vClass="passenger" color="green"/>
    <vehicle id="Flow16.0" type="Car16" depart="0.00" fromTaz="cluster3086736522_655375108_655375247_655375401_#1more" toTaz="cluster655375228_655375240">
        <routeDistribution last="0">
            <route cost="167.43" probability="0.68931847" edges="594658762#0"/>
            <route cost="241.68" probability="0.31068153" edges="594658760#0 49695736#0 300077497#0 300077497#6 E1"/>
        </routeDistribution>
    </vehicle>
    <vType id="Car17" length="5.00" vClass="passenger" color="green"/>
    <vehicle id="Flow17.0" type="Car17" depart="0.00" fromTaz="cluster_5372642442_631668976_631668981_631669076" toTaz="2690921409">
        <routeDistribution last="0">
            <route cost="37.61" probability="1.00000000" edges="506322851#0"/>
        </routeDistribution>
    </vehicle>
    <vType id="Car18" length="5.00" vClass="passenger" color="green"/>
    <vehicle id="Flow18.0" type="Car18" depart="0.00" fromTaz="3208478132" toTaz="656132498">
        <routeDistribution last="0">
            <route cost="119.29" probability="1.00000000" edges="51289045#3 51392936#0"/>
        </routeDistribution>
    </vehicle>
    <vType id="Car19" length="5.00" vClass="passenger" color="green"/>
    <vehicle id="Flow19.0" type="Car19" depart="0.00" fromTaz="3208478128" toTaz="3208478132">
        <routeDistribution last="0">
            <route cost="7.77" probability="1.00000000" edges="314800955"/>
        </routeDistribution>
    </vehicle>
    <vType id="Car2" length="5.00" vClass="passenger" color="green"/>
    <vehicle id="Flow2.0" type="Car2" depart="0.00" fromTaz="cluster655375228_655375240" toTaz="3208478132">
        <routeDistribution last="0">
            <route cost="305.22" probability="0.43331621" edges="-E1 -300077497#8 -300077497#5 182334378#0 232003903#0 51289045#1"/>
            <route cost="281.65" probability="0.56668379" edges="-E1 263217604#0 360843888 244450512#4 314800955"/>
        </routeDistribution>
    </vehicle>
    <vType id="Car20" length="5.00" vClass="passenger" color="green"/>
    <vehicle id="Flow20.0" type="Car20" depart="0.00" fromTaz="cluster_623980090_623980094" toTaz="7782558675">
        <routeDistribution last="0">
            <route cost="25.15" probability="1.00000000" edges="196961379#0"/>
        </routeDistribution>
    </vehicle>
    <vType id="Car21" length="5.00" vClass="passenger" color="green"/>
    <vehicle id="Flow21.0" type="Car21" depart="0.00" fromTaz="622618197" toTaz="622618015">
        <routeDistribution last="0">
            <route cost="0.22" probability="1.00000000" edges="593849721"/>
        </routeDistribution>
    </vehicle>
    <vType id="Car22" length="5.00" vClass="passenger" color="green"/>
    <vehicle id="Flow22.0" type="Car22" depart="0.00" fromTaz="655375286" toTaz="cluster655375336_end_0_655375336_end_1_655375336_end_10_655375336_end_11_#8more">
        <routeDistribution last="0">
            <route cost="106.75" probability="0.68132436" edges="244450512#0 244450512#1 244450512#4 244450512#5 593844221#0"/>
            <route cost="190.59" probability="0.31867564" edges="244450512#0 51362431 594658760#0"/>
        </routeDistribution>
    </vehicle>
    <vType id="Car23" length="5.00" vClass="passenger" color="green"/>
    <vehicle id="Flow23.0" type="Car23" depart="0.00" fromTaz="622618112" toTaz="622618197">
        <routeDistribution last="0">
            <route cost="7.27" probability="1.00000000" edges="593847702#3"/>
        </routeDistribution>
    </vehicle>
    <vType id="Car24" length="5.00" vClass="passenger" color="green"/>
    <vehicle id="Flow24.0" type="Car24" depart="0.00" fromTaz="3092676101" toTaz="cluster_623980090_623980094">
        <routeDistribution last="0">
            <route cost="52.23" probability="1.00000000" edges="268564473#0 288878927"/>
        </routeDistribution>
    </vehicle>
    <vType id="Car3" length="5.00" vClass="passenger" color="green"/>
    <vehicle id="Flow3.0" type="Car3" depart="0.00" fromTaz="cluster655375336_end_0_655375336_end_1_655375336_end_10_655375336_end_11_#8more" toTaz="656132476">
        <routeDistribution last="0">
            <route cost="147.77" probability="0.49329801" edges="232003903#0 51289045#1 51289045#3 51289045#4 51289045#5 -260882327"/>
            <route cost="182.79" probability="0.50670199" edges="232003903#0 593844216#0 545977624#0"/>
        </routeDistribution>
    </vehicle>
    <vType id="Car4" length="5.00" vClass="passenger" color="green"/>
    <vehicle id="Flow4.0" type="Car4" depart="0.00" fromTaz="622618230" toTaz="2013717678">
        <routeDistribution last="1">
            <route cost="285.19" probability="0.53350074" edges="593849715 -593847704#2 593847705 593847703#0 182334379#0 288135628#0"/>
            <route cost="331.43" probability="0.46649926" edges="593849715 49073272#0 49073272#1 49073272#3 49073272#4 353392316#0 288135628#0"/>
        </routeDistribution>
    </vehicle>
    <vType id="Car5" length="5.00" vClass="passenger" color="green"/>
    <vehicle id="Flow5.0" type="Car5" depart="0.00" fromTaz="7782558678" toTaz="3431431576">
        <routeDistribution last="1">
            <route cost="139.72" probability="0.51257025" edges="196961215#0 196961215#2 241518668#0 336063376#0"/>
            <route cost="247.33" probability="0.48742975" edges="196961215#0 196961215#2 288878926#0 593849711#0"/>
        </routeDistribution>
    </vehicle>
    <vType id="Car6" length="5.00" vClass="passenger" color="green"/>
    <vehicle id="Flow6.0" type="Car6" depart="0.00" fromTaz="6251747844" toTaz="cluster_5372642442_631668976_631668981_631669076">
        <routeDistribution last="0">
            <route cost="396.04" probability="1.00000000" edges="-260882327 -545977624#2 593842812#0 593842812#2 593844221#0 49695736#0 182334379#0"/>
        </routeDistribution>
    </vehicle>
    <vType id="Car7" length="5.00" vClass="passenger" color="green"/>
    <vehicle id="Flow7.0" type="Car7" depart="0.00" fromTaz="631668821" toTaz="631668821">
        <routeDistribution last="0">
            <route cost="190.89" probability="1.00000000" edges="-49695726 49695726"/>
        </routeDistribution>
    </vehicle>
    <vType id="Car8" length="5.00" vClass="passenger" color="green"/>
    <vehicle id="Flow8.0" type="Car8" depart="0.00" fromTaz="622618144" toTaz="2713733789">
        <routeDistribution last="0">
            <route cost="122.64" probability="1.00000000" edges="593852345#0 196961378#1"/>
        </routeDistribution>
    </vehicle>
    <vType id="Car9" length="5.00" vClass="passenger" color="green"/>
    <vehicle id="Flow9.0" type="Car9" depart="0.00" fromTaz="2760755470" toTaz="655375241">
        <routeDistribution last="0">
            <route cost="117.49" probability="0.56832309" edges="30620492#0 30620492#1 506322840#0"/>
            <route cost="158.65" probability="0.43167691" edges="30620492#0 30620492#1 506322844#0 E1 1334905223#0"/>
        </routeDistribution>
    </vehicle>
    <vehicle id="Flow17.1" type="Car17" depart="15.79" fromTaz="cluster_5372642442_631668976_631668981_631669076" toTaz="2690921409">
        <routeDistribution last="0">
            <route cost="50.58" probability="1.00000000" edges="506322851#0"/>
        </routeDistribution>
    </vehicle>
    <vehicle id="Flow7.1" type="Car7" depart="21.43" fromTaz="631668821" toTaz="631668821">
        <routeDistribution last="0">
            <route cost="161.86" probability="1.00000000" edges="-49695726 49695726"/>
        </routeDistribution>
    </vehicle>
    <vehicle id="Flow10.1" type="Car10" depart="23.08" fromTaz="cluster619136880_619136881_cluster_4510442270_5296993511_5296993513_619136931_#1more" toTaz="6252193077">
        <routeDistribution last="0">
            <route cost="117.60" probability="1.00000000" edges="196961377#0 196961377#3 593849718#0"/>
        </routeDistribution>
    </vehicle>
    <vehicle id="Flow12.1" type="Car12" depart="23.08" fromTaz="cluster_9383263990_9383263991_9383263992_9383263993" toTaz="cluster_9383263990_9383263991_9383263992_9383263993">
        <routeDistribution last="1">
            <route cost="60.90" probability="0.50399635" edges="506322841#1 182336886 30620492#1"/>
            <route cost="131.79" probability="0.15723309" edges="506322844#0 -300077497#8 35274074#0 506322848#0"/>
            <route cost="94.49" probability="0.33877056" edges="506322840#0 -1334905223#2 263217603#0"/>
        </routeDistribution>
    </vehicle>
    <vehicle id="Flow15.1" type="Car15" depart="23.08" fromTaz="cluster619136880_619136881_cluster_4510442270_5296993511_5296993513_619136931_#1more" toTaz="622618165">
        <routeDistribution last="0">
            <route cost="138.77" probability="1.00000000" edges="48794887#0"/>
        </routeDistribution>
    </vehicle>
    <vehicle id="Flow17.2" type="Car17" depart="31.58" fromTaz="cluster_5372642442_631668976_631668981_631669076" toTaz="2690921409">
        <routeDistribution last="0">
            <route cost="81.78" probability="1.00000000" edges="506322851#0"/>
        </routeDistribution>
    </vehicle>
    <vehicle id="Flow4.1" type="Car4" depart="33.33" fromTaz="622618230" toTaz="2013717678">
        <routeDistribution last="1">
            <route cost="356.72" probability="0.50957866" edges="593849715 49073272#0 49073272#1 49073272#3 49073272#4 353392316#0 288135628#0"/>
            <route cost="385.35" probability="0.49042134" edges="593849715 -593847704#2 593847705 593847703#0 182334379#0 288135628#0"/>
        </routeDistribution>
    </vehicle>
    <vehicle id="Flow7.2" type="Car7" depart="42.86" fromTaz="631668821" toTaz="631668821">
        <routeDistribution last="0">
            <route cost="142.98" probability="1.00000000" edges="-49695726 49695726"/>
        </routeDistribution>
    </vehicle>
    <vehicle id="Flow21.1" type="Car21" depart="42.86" fromTaz="622618197" toTaz="622618015">
        <routeDistribution last="0">
            <route cost="0.09" probability="1.00000000" edges="593849721"/>
        </routeDistribution>
    </vehicle>
    <vehicle id="Flow10.2" type="Car10" depart="46.15" fromTaz="cluster619136880_619136881_cluster_4510442270_5296993511_5296993513_619136931_#1more" toTaz="6252193077">
        <routeDistribution last="0">
            <route cost="265.80" probability="1.00000000" edges="196961377#0 196961377#3 593849718#0"/>
        </routeDistribution>
    </vehicle>
    <vehicle id="Flow12.2" type="Car12" depart="46.15" fromTaz="cluster_9383263990_9383263991_9383263992_9383263993" toTaz="cluster_9383263990_9383263991_9383263992_9383263993">
        <routeDistribution last="0">
            <route cost="67.01" probability="0.62194831" edges="506322841#1 182336886 30620492#1"/>
            <route cost="130.52" probability="0.37805169" edges="506322840#0 -1334905223#2 263217603#0"/>
        </routeDistribution>
    </vehicle>
    <vehicle id="Flow15.2" type="Car15" depart="46.15" fromTaz="cluster619136880_619136881_cluster_4510442270_5296993511_5296993513_619136931_#1more" toTaz="622618165">
        <routeDistribution last="0">
            <route cost="208.20" probability="1.00000000" edges="48794887#0"/>
        </routeDistribution>
    </vehicle>
    <vehicle id="Flow17.3" type="Car17" depart="47.37" fromTaz="cluster_5372642442_631668976_631668981_631669076" toTaz="2690921409">
        <routeDistribution last="0">
            <route cost="71.55" probability="1.00000000" edges="506322851#0"/>
        </routeDistribution>
    </vehicle>
    <vehicle id="Flow2.1" type="Car2" depart="50.00" fromTaz="cluster655375228_655375240" toTaz="3208478132">
        <routeDistribution last="0">
            <route cost="233.07" probability="0.35350694" edges="-E1 263217604#0 360843888 244450512#4 314800955"/>
            <route cost="358.60" probability="0.33004256" edges="-E1 -300077497#8 -300077497#5 182334378#0 232003903#0 51289045#1"/>
            <route cost="351.66" probability="0.31645049" edges="263217603#0 506322842#0 506322846#0 506322846#2 288135626#0 1068234499#0 182334378#0 232003903#0 51289045#1"/>
        </routeDistribution>
    </vehicle>
    <vehicle id="Flow5.1" type="Car5" depart="50.00" fromTaz="7782558678" toTaz="3431431576">
        <routeDistribution last="0">
            <route cost="127.12" probability="0.47028984" edges="196961215#0 196961215#2 288878926#0 593849711#0"/>
            <route cost="130.30" probability="0.52971016" edges="196961215#0 196961215#2 241518668#0 336063376#0"/>
        </routeDistribution>
    </vehicle>
    <vehicle id="Flow13.1" type="Car13" depart="60.00" fromTaz="622618015" toTaz="622618230">
        <routeDistribution last="0">
            <route cost="42.72" probability="1.00000000" edges="49073274 593852346"/>
        </routeDistribution>
    </vehicle>
    <vehicle id="Flow17.4" type="Car17" depart="63.16" fromTaz="cluster_5372642442_631668976_631668981_631669076" toTaz="2690921409">
        <routeDistribution last="0">
            <route cost="22.73" probability="1.00000000" edges="506322851#0"/>
        </routeDistribution>
    </vehicle>
    <vehicle id="Flow7.3" type="Car7" depart="64.28" fromTaz="631668821" toTaz="631668821">
        <routeDistribution last="0">
            <route cost="65.80" probability="1.00000000" edges="-49695726 49695726"/>
        </routeDistribution>
    </vehicle>
    <vehicle id="Flow4.2" type="Car4" depart="66.67" fromTaz="622618230" toTaz="2013717678">
        <routeDistribution last="1">
            <route cost="255.75" probability="0.40806484" edges="593849711#0 593849711#2 593847701 593847705 593847703#0 182334379#0 288135628#0"/>
            <route cost="380.48" probability="0.28832790" edges="593849715 49073272#0 49073272#1 49073272#3 49073272#4 353392316#0 288135628#0"/>
            <route cost="368.06" probability="0.30360726" edges="593849715 -593847704#2 593847705 593847703#0 182334379#0 288135628#0"/>
        </routeDistribution>
    </vehicle>
    <vehicle id="Flow10.3" type="Car10" depart="69.23" fromTaz="cluster619136880_619136881_cluster_4510442270_5296993511_5296993513_619136931_#1more" toTaz="6252193077">
        <routeDistribution last="0">
            <route cost="235.45" probability="1.00000000" edges="196961377#0 196961377#3 593849718#0"/>
        </routeDistribution>
    </vehicle>
    <vehicle id="Flow12.3" type="Car12" depart="69.23" fromTaz="cluster_9383263990_9383263991_9383263992_9383263993" toTaz="cluster_9383263990_9383263991_9383263992_9383263993">
        <routeDistribution last="1">
            <route cost="39.57" probability="0.63572148" edges="506322841#1 182336886 30620492#1"/>
            <route cost="84.64" probability="0.36427852" edges="506322840#0 -1334905223#2 263217603#0"/>
        </routeDistribution>
    </vehicle>
    <vehicle id="Flow15.3" type="Car15" depart="69.23" fromTaz="cluster619136880_619136881_cluster_4510442270_5296993511_5296993513_619136931_#1more" toTaz="622618165">
        <routeDistribution last="0">
            <route cost="124.53" probability="1.00000000" edges="48794887#0"/>
        </routeDistribution>
    </vehicle>
    <vehicle id="Flow0.1" type="Car0" depart="75.00" fromTaz="cluster_3431431575_4777363357_655375231_6982059025" toTaz="3196998953">
        <routeDistribution last="2">
            <route cost="319.36" probability="0.33721564" edges="51362429#0 593847701 E0 1334904386#0 303647015#0"/>
            <route cost="324.39" probability="0.33391185" edges="484988952#0 -51362430 1068440001 1239087513 593844221#0 -594658757#2 303647015#0"/>
            <route cost="403.79" probability="0.32887252" edges="51362429#0 1068440006#0 -594658757#2 303647015#0"/>
        </routeDistribution>
    </vehicle>
    <vehicle id="Flow1.1" type="Car1" depart="75.00" fromTaz="631668923" toTaz="622618112">
        <routeDistribution last="1">
            <route cost="429.31" probability="0.27977487" edges="1068234498#0 288135626#0 1068234499#0 182334378#0 1068440004#1 593847702#0"/>
            <route cost="267.94" probability="0.36283908" edges="1068234498#0 288135626#0 1068234499#0 -593847703#3 -593847705 593847704#0 49073272#0"/>
            <route cost="254.14" probability="0.35738605" edges="1068234498#0 288135626#0 1068234499#0 -593847703#3 593847702#0"/>
        </routeDistribution>
    </vehicle>
    <vehicle id="Flow6.1" type="Car6" depart="75.00" fromTaz="6251747844" toTaz="cluster_5372642442_631668976_631668981_631669076">
        <routeDistribution last="0">
            <route cost="301.52" probability="1.00000000" edges="-260882327 -545977624#2 593842812#0 593842812#2 593844221#0 49695736#0 182334379#0"/>
        </routeDistribution>
    </vehicle>
    <vehicle id="Flow17.5" type="Car17" depart="78.95" fromTaz="cluster_5372642442_631668976_631668981_631669076" toTaz="2690921409">
        <routeDistribution last="0">
            <route cost="144.95" probability="1.00000000" edges="506322851#0"/>
        </routeDistribution>
    </vehicle>
    <vehicle id="Flow7.4" type="Car7" depart="85.71" fromTaz="631668821" toTaz="631668821">
        <routeDistribution last="0">
            <route cost="186.51" probability="1.00000000" edges="-49695726 49695726"/>
        </routeDistribution>
    </vehicle>
    <vehicle id="Flow21.2" type="Car21" depart="85.71" fromTaz="622618197" toTaz="622618015">
        <routeDistribution last="0">
            <route cost="0.22" probability="1.00000000" edges="593849721"/>
        </routeDistribution>
    </vehicle>
    <vehicle id="Flow10.4" type="Car10" depart="92.30" fromTaz="cluster619136880_619136881_cluster_4510442270_5296993511_5296993513_619136931_#1more" toTaz="6252193077">
        <routeDistribution last="0">
            <route cost="247.67" probability="1.00000000" edges="196961377#0 196961377#3 593849718#0"/>
        </routeDistribution>
    </vehicle>
    <vehicle id="Flow12.4" type="Car12" depart="92.30" fromTaz="cluster_9383263990_9383263991_9383263992_9383263993" toTaz="cluster_9383263990_9383263991_9383263992_9383263993">
        <routeDistribution last="1">
            <route cost="69.23" probability="0.63378982" edges="506322841#1 182336886 30620492#1"/>
            <route cost="72.66" probability="0.36621018" edges="506322840#0 -1334905223#2 263217603#0"/>
        </routeDistribution>
    </vehicle>
    <vehicle id="Flow15.4" type="Car15" depart="92.30" fromTaz="cluster619136880_619136881_cluster_4510442270_5296993511_5296993513_619136931_#1more" toTaz="622618165">
        <routeDistribution last="0">
            <route cost="211.43" probability="1.00000000" edges="48794887#0"/>
        </routeDistribution>
    </vehicle>
    <vehicle id="Flow17.6" type="Car17" depart="94.73" fromTaz="cluster_5372642442_631668976_631668981_631669076" toTaz="2690921409">
        <routeDistribution last="0">
            <route cost="77.36" probability="1.00000000" edges="506322851#0"/>
        </routeDistribution>
    </vehicle>
    <vehicle id="Flow4.3" type="Car4" depart="100.00" fromTaz="622618230" toTaz="2013717678">
        <routeDistribution last="2">
            <route cost="458.66" probability="0.31128105" edges="593849715 49073272#0 49073272#1 49073272#3 49073272#4 353392316#0 288135628#0"/>
            <route cost="482.90" probability="0.34661231" edges="593849711#0 593849711#2 593847701 593847705 593847703#0 182334379#0 288135628#0"/>
            <route cost="424.11" probability="0.34210664" edges="593849715 -593847704#2 593847705 593847703#0 182334379#0 288135628#0"/>
        </routeDistribution>
    </vehicle>
    <vehicle id="Flow11.1" type="Car11" depart="100.00" fromTaz="cluster_9383263990_9383263991_9383263992_9383263993" toTaz="3139323041">
        <routeDistribution last="0">
            <route cost="66.76" probability="1.00000000" edges="506322841#1 198001764#0 182336887#2"/>
        </routeDistribution>
    </vehicle>
    <vehicle id="Flow2.2" type="Car2" depart="100.00" fromTaz="cluster655375228_655375240" toTaz="3208478132">
        <routeDistribution last="0">
            <route cost="240.96" probability="0.50041981" edges="-E1 263217604#0 360843888 244450512#4 314800955"/>
            <route cost="219.05" probability="0.49958019" edges="-E1 -300077497#8 -300077497#5 182334378#0 232003903#0 51289045#1"/>
        </routeDistribution>
    </vehicle>
    <vehicle id="Flow3.1" type="Car3" depart="100.00" fromTaz="cluster655375336_end_0_655375336_end_1_655375336_end_10_655375336_end_11_#8more" toTaz="656132476">
        <routeDistribution last="0">
            <route cost="150.18" probability="0.50150305" edges="232003903#0 51289045#1 51289045#3 51289045#4 51289045#5 -260882327"/>
            <route cost="132.34" probability="0.49849695" edges="232003903#0 593844216#0 545977624#0"/>
        </routeDistribution>
    </vehicle>
    <vehicle id="Flow5.2" type="Car5" depart="100.00" fromTaz="7782558678" toTaz="3431431576">
        <routeDistribution last="0">
            <route cost="220.04" probability="1.00000000" edges="196961215#0 196961215#2 241518668#0 336063376#0"/>
        </routeDistribution>
    </vehicle>
    <vehicle id="Flow7.5" type="Car7" depart="107.14" fromTaz="631668821" toTaz="631668821">
        <routeDistribution last="0">
            <route cost="218.18" probability="1.00000000" edges="-49695726 49695726"/>
        </routeDistribution>
    </vehicle>
    <vehicle id="Flow17.7" type="Car17" depart="110.52" fromTaz="cluster_5372642442_631668976_631668981_631669076" toTaz="2690921409">
        <routeDistribution last="0">
            <route cost="115.86" probability="1.00000000" edges="506322851#0"/>
        </routeDistribution>
    </vehicle>
    <vehicle id="Flow10.5" type="Car10" depart="115.38" fromTaz="cluster619136880_619136881_cluster_4510442270_5296993511_5296993513_619136931_#1more" toTaz="6252193077">
        <routeDistribution last="0">
            <route cost="150.61" probability="1.00000000" edges="196961377#0 196961377#3 593849718#0"/>
        </routeDistribution>
    </vehicle>
    <vehicle id="Flow12.5" type="Car12" depart="115.38" fromTaz="cluster_9383263990_9383263991_9383263992_9383263993" toTaz="cluster_9383263990_9383263991_9383263992_9383263993">
        <routeDistribution last="1">
            <route cost="98.15" probability="0.55650959" edges="506322841#1 182336886 30620492#1"/>
            <route cost="116.07" probability="0.44349041" edges="506322840#0 -1334905223#2 263217603#0"/>
        </routeDistribution>
    </vehicle>
    <vehicle id="Flow15.5" type="Car15" depart="115.38" fromTaz="cluster619136880_619136881_cluster_4510442270_5296993511_5296993513_619136931_#1more" toTaz="622618165">
        <routeDistribution last="0">
            <route cost="228.89" probability="1.00000000" edges="48794887#0"/>
        </routeDistribution>
    </vehicle>
    <vehicle id="Flow13.2" type="Car13" depart="120.00" fromTaz="622618015" toTaz="622618230">
        <routeDistribution last="0">
            <route cost="29.41" probability="1.00000000" edges="49073274 593852346"/>
        </routeDistribution>
    </vehicle>
    <vehicle id="Flow17.8" type="Car17" depart="126.31" fromTaz="cluster_5372642442_631668976_631668981_631669076" toTaz="2690921409">
        <routeDistribution last="0">
            <route cost="23.53" probability="1.00000000" edges="506322851#0"/>
        </routeDistribution>
    </vehicle>
    <vehicle id="Flow7.6" type="Car7" depart="128.57" fromTaz="631668821" toTaz="631668821">
        <routeDistribution last="0">
            <route cost="138.19" probability="1.00000000" edges="-49695726 49695726"/>
        </routeDistribution>
    </vehicle>
    <vehicle id="Flow21.3" type="Car21" depart="128.57" fromTaz="622618197" toTaz="622618015">
        <routeDistribution last="0">
            <route cost="0.04" probability="1.00000000" edges="593849721"/>
        </routeDistribution>
    </vehicle>
    <vehicle id="Flow4.4" type="Car4" depart="133.33" fromTaz="622618230" toTaz="2013717678">
        <routeDistribution last="2">
            <route cost="475.14" probability="0.24913166" edges="593849715 49073272#0 49073272#1 49073272#3 49073272#4 353392316#0 288135628#0"/>
            <route cost="309.34" probability="0.43349047" edges="593849715 -593847704#2 593847705 593847703#0 182334379#0 288135628#0"/>
            <route cost="451.10" probability="0.31737788" edges="593849711#0 593849711#2 593847701 593847705 593847703#0 182334379#0 288135628#0"/>
        </routeDistribution>
    </vehicle>
    <vehicle id="Flow10.6" type="Car10" depart="138.46" fromTaz="cluster619136880_619136881_cluster_4510442270_5296993511_5296993513_619136931_#1more" toTaz="6252193077">
        <routeDistribution last="0">
            <route cost="211.15" probability="1.00000000" edges="196961377#0 196961377#3 593849718#0"/>
        </routeDistribution>
    </vehicle>
    <vehicle id="Flow12.6" type="Car12" depart="138.46" fromTaz="cluster_9383263990_9383263991_9383263992_9383263993" toTaz="cluster_9383263990_9383263991_9383263992_9383263993">
        <routeDistribution last="0">
            <route cost="77.40" probability="1.00000000" edges="506322841#1 182336886 30620492#1"/>
        </routeDistribution>
    </vehicle>
    <vehicle id="Flow15.6" type="Car15" depart="138.46" fromTaz="cluster619136880_619136881_cluster_4510442270_5296993511_5296993513_619136931_#1more" toTaz="622618165">
        <routeDistribution last="0">
            <route cost="207.05" probability="1.00000000" edges="48794887#0"/>
        </routeDistribution>
    </vehicle>
    <vehicle id="Flow17.9" type="Car17" depart="142.10" fromTaz="cluster_5372642442_631668976_631668981_631669076" toTaz="2690921409">
        <routeDistribution last="0">
            <route cost="106.61" probability="1.00000000" edges="506322851#0"/>
        </routeDistribution>
    </vehicle>
    <vehicle id="Flow7.7" type="Car7" depart="150.00" fromTaz="631668821" toTaz="631668821">
        <routeDistribution last="0">
            <route cost="133.70" probability="1.00000000" edges="-49695726 49695726"/>
        </routeDistribution>
    </vehicle>
    <vehicle id="Flow0.2" type="Car0" depart="150.00" fromTaz="cluster_3431431575_4777363357_655375231_6982059025" toTaz="3196998953">
        <routeDistribution last="0">
            <route cost="283.57" probability="0.39663881" edges="51362429#0 593847701 E0 -594658757#2 303647015#0"/>
            <route cost="385.94" probability="0.29116302" edges="484988952#0 -51362430 1068440001 1239087513 593844221#0 -594658757#2 303647015#0"/>
            <route cost="536.49" probability="0.31219817" edges="51362429#0 1068440006#0 -594658757#2 303647015#0"/>
        </routeDistribution>
    </vehicle>
    <vehicle id="Flow1.2" type="Car1" depart="150.00" fromTaz="631668923" toTaz="622618112">
        <routeDistribution last="0">
            <route cost="319.36" probability="0.52905055" edges="1068234498#0 288135626#0 1068234499#0 -593847703#3 593847702#0"/>
            <route cost="500.86" probability="0.47094945" edges="1068234498#0 288135626#0 1068234499#0 182334378#0 1068440004#1 -593847705 593847704#0 49073272#0"/>
        </routeDistribution>
    </vehicle>
    <vehicle id="Flow19.1" type="Car19" depart="150.00" fromTaz="3208478128" toTaz="3208478132">
        <routeDistribution last="0">
            <route cost="1.89" probability="1.00000000" edges="314800955"/>
        </routeDistribution>
    </vehicle>
    <vehicle id="Flow2.3" type="Car2" depart="150.00" fromTaz="cluster655375228_655375240" toTaz="3208478132">
        <routeDistribution last="1">
            <route cost="200.51" probability="0.52733821" edges="-E1 -300077497#8 -300077497#5 182334378#0 232003903#0 51289045#1"/>
            <route cost="306.68" probability="0.47266179" edges="-E1 263217604#0 360843888 244450512#4 314800955"/>
        </routeDistribution>
    </vehicle>
    <vehicle id="Flow5.3" type="Car5" depart="150.00" fromTaz="7782558678" toTaz="3431431576">
        <routeDistribution last="1">
            <route cost="138.97" probability="0.49878392" edges="196961215#0 196961215#2 241518668#0 336063376#0"/>
            <route cost="136.29" probability="0.50121608" edges="196961215#0 196961215#2 288878926#0 593849711#0"/>
        </routeDistribution>
    </vehicle>
    <vehicle id="Flow6.2" type="Car6" depart="150.00" fromTaz="6251747844" toTaz="cluster_5372642442_631668976_631668981_631669076">
        <routeDistribution last="0">
            <route cost="233.97" probability="1.00000000" edges="-260882327 -545977624#2 593842812#0 593842812#2 593844221#0 49695736#0 182334379#0"/>
        </routeDistribution>
    </vehicle>
    <vehicle id="Flow9.1" type="Car9" depart="150.00" fromTaz="2760755470" toTaz="655375241">
        <routeDistribution last="1">
            <route cost="162.30" probability="0.48250793" edges="30620492#0 30620492#1 506322840#0"/>
            <route cost="123.10" probability="0.51749207" edges="30620492#0 30620492#1 506322844#0 E1 1334905223#0"/>
        </routeDistribution>
    </vehicle>
    <vehicle id="Flow17.10" type="Car17" depart="157.89" fromTaz="cluster_5372642442_631668976_631668981_631669076" toTaz="2690921409">
        <routeDistribution last="0">
            <route cost="129.46" probability="1.00000000" edges="506322851#0"/>
        </routeDistribution>
    </vehicle>
    <vehicle id="Flow10.7" type="Car10" depart="161.53" fromTaz="cluster619136880_619136881_cluster_4510442270_5296993511_5296993513_619136931_#1more" toTaz="6252193077">
        <routeDistribution last="0">
            <route cost="225.83" probability="1.00000000" edges="196961377#0 196961377#3 593849718#0"/>
        </routeDistribution>
    </vehicle>
    <vehicle id="Flow12.7" type="Car12" depart="161.53" fromTaz="cluster_9383263990_9383263991_9383263992_9383263993" toTaz="cluster_9383263990_9383263991_9383263992_9383263993">
        <routeDistribution last="1">
            <route cost="91.74" probability="0.49591188" edges="506322841#1 182336886 30620492#1"/>
            <route cost="85.93" probability="0.50408812" edges="506322840#0 -1334905223#2 263217603#0"/>
        </routeDistribution>
    </vehicle>
    <vehicle id="Flow15.7" type="Car15" depart="161.53" fromTaz="cluster619136880_619136881_cluster_4510442270_5296993511_5296993513_619136931_#1more" toTaz="622618165">
        <routeDistribution last="0">
            <route cost="32.11" probability="1.00000000" edges="48794887#0"/>
        </routeDistribution>
    </vehicle>
    <vehicle id="Flow4.5" type="Car4" depart="166.67" fromTaz="622618230" toTaz="2013717678">
        <routeDistribution last="0">
            <route cost="457.46" probability="0.35519248" edges="593849711#0 593849711#2 593847701 593847705 593847703#0 182334379#0 288135628#0"/>
            <route cost="503.55" probability="0.40082575" edges="593849715 -593847704#2 593847705 593847703#0 182334379#0 288135628#0"/>
            <route cost="576.18" probability="0.24398178" edges="593849715 49073272#0 49073272#1 49073272#3 49073272#4 353392316#0 288135628#0"/>
        </routeDistribution>
    </vehicle>
    <vehicle id="Flow7.8" type="Car7" depart="171.42" fromTaz="631668821" toTaz="631668821">
        <routeDistribution last="0">
            <route cost="141.00" probability="1.00000000" edges="-49695726 49695726"/>
        </routeDistribution>
    </vehicle>
    <vehicle id="Flow21.4" type="Car21" depart="171.43" fromTaz="622618197" toTaz="622618015">
        <routeDistribution last="0">
            <route cost="0.20" probability="1.00000000" edges="593849721"/>
        </routeDistribution>
    </vehicle>
    <vehicle id="Flow17.11" type="Car17" depart="173.68" fromTaz="cluster_5372642442_631668976_631668981_631669076" toTaz="2690921409">
        <routeDistribution last="0">
            <route cost="64.66" probability="1.00000000" edges="506322851#0"/>
        </routeDistribution>
    </vehicle>
    <vehicle id="Flow13.3" type="Car13" depart="180.00" fromTaz="622618015" toTaz="622618230">
        <routeDistribution last="0">
            <route cost="14.21" probability="1.00000000" edges="49073274 593852346"/>
        </routeDistribution>
    </vehicle>
    <vehicle id="Flow10.8" type="Car10" depart="184.61" fromTaz="cluster619136880_619136881_cluster_4510442270_5296993511_5296993513_619136931_#1more" toTaz="6252193077">
        <routeDistribution last="0">
            <route cost="238.13" probability="1.00000000" edges="196961377#0 196961377#3 593849718#0"/>
        </routeDistribution>
    </vehicle>
    <vehicle id="Flow12.8" type="Car12" depart="184.61" fromTaz="cluster_9383263990_9383263991_9383263992_9383263993" toTaz="cluster_9383263990_9383263991_9383263992_9383263993">
        <routeDistribution last="0">
            <route cost="58.25" probability="1.00000000" edges="506322841#1 182336886 30620492#1"/>
        </routeDistribution>
    </vehicle>
    <vehicle id="Flow15.8" type="Car15" depart="184.61" fromTaz="cluster619136880_619136881_cluster_4510442270_5296993511_5296993513_619136931_#1more" toTaz="622618165">
        <routeDistribution last="0">
            <route cost="73.81" probability="1.00000000" edges="48794887#0"/>
        </routeDistribution>
    </vehicle>
    <vehicle id="Flow17.12" type="Car17" depart="189.47" fromTaz="cluster_5372642442_631668976_631668981_631669076" toTaz="2690921409">
        <routeDistribution last="0">
            <route cost="107.42" probability="1.00000000" edges="506322851#0"/>
        </routeDistribution>
    </vehicle>
    <vehicle id="Flow7.9" type="Car7" depart="192.85" fromTaz="631668821" toTaz="631668821">
        <routeDistribution last="0">
            <route cost="189.69" probability="1.00000000" edges="-49695726 49695726"/>
        </routeDistribution>
    </vehicle>
    <vehicle id="Flow4.6" type="Car4" depart="200.00" fromTaz="622618230" toTaz="2013717678">
        <routeDistribution last="1">
            <route cost="389.73" probability="0.49504318" edges="593849715 -593847704#2 593847705 593847703#0 182334379#0 288135628#0"/>
            <route cost="421.87" probability="0.50495682" edges="593849711#0 593849711#2 593847701 593847705 593847703#0 182334379#0 288135628#0"/>
        </routeDistribution>
    </vehicle>
    <vehicle id="Flow11.2" type="Car11" depart="200.00" fromTaz="cluster_9383263990_9383263991_9383263992_9383263993" toTaz="3139323041">
        <routeDistribution last="0">
            <route cost="67.60" probability="1.00000000" edges="506322841#1 198001764#0 182336887#2"/>
        </routeDistribution>
    </vehicle>
    <vehicle id="Flow2.4" type="Car2" depart="200.00" fromTaz="cluster655375228_655375240" toTaz="3208478132">
        <routeDistribution last="1">
            <route cost="167.83" probability="0.55791923" edges="-E1 263217604#0 360843888 244450512#4 314800955"/>
            <route cost="301.51" probability="0.44208077" edges="-E1 -300077497#8 -300077497#5 182334378#0 232003903#0 51289045#1"/>
        </routeDistribution>
    </vehicle>
    <vehicle id="Flow3.2" type="Car3" depart="200.00" fromTaz="cluster655375336_end_0_655375336_end_1_655375336_end_10_655375336_end_11_#8more" toTaz="656132476">
        <routeDistribution last="0">
            <route cost="132.65" probability="0.52241975" edges="232003903#0 51289045#1 51289045#3 51289045#4 51289045#5 -260882327"/>
            <route cost="151.83" probability="0.47758025" edges="232003903#0 593844216#0 545977624#0"/>
        </routeDistribution>
    </vehicle>
    <vehicle id="Flow5.4" type="Car5" depart="200.00" fromTaz="7782558678" toTaz="3431431576">
        <routeDistribution last="0">
            <route cost="132.33" probability="0.52875339" edges="196961215#0 196961215#2 241518668#0 336063376#0"/>
            <route cost="213.23" probability="0.47124661" edges="196961215#0 196961215#2 288878926#0 593849711#0"/>
        </routeDistribution>
    </vehicle>
    <vehicle id="Flow17.13" type="Car17" depart="205.26" fromTaz="cluster_5372642442_631668976_631668981_631669076" toTaz="2690921409">
        <routeDistribution last="0">
            <route cost="133.07" probability="1.00000000" edges="506322851#0"/>
        </routeDistribution>
    </vehicle>
    <vehicle id="Flow10.9" type="Car10" depart="207.68" fromTaz="cluster619136880_619136881_cluster_4510442270_5296993511_5296993513_619136931_#1more" toTaz="6252193077">
        <routeDistribution last="0">
            <route cost="226.11" probability="1.00000000" edges="196961377#0 196961377#3 593849718#0"/>
        </routeDistribution>
    </vehicle>
    <vehicle id="Flow12.9" type="Car12" depart="207.68" fromTaz="cluster_9383263990_9383263991_9383263992_9383263993" toTaz="cluster_9383263990_9383263991_9383263992_9383263993">
        <routeDistribution last="0">
            <route cost="59.18" probability="1.00000000" edges="506322841#1 182336886 30620492#1"/>
        </routeDistribution>
    </vehicle>
    <vehicle id="Flow15.9" type="Car15" depart="207.68" fromTaz="cluster619136880_619136881_cluster_4510442270_5296993511_5296993513_619136931_#1more" toTaz="622618165">
        <routeDistribution last="0">
            <route cost="200.66" probability="1.00000000" edges="48794887#0"/>
        </routeDistribution>
    </vehicle>
    <vehicle id="Flow7.10" type="Car7" depart="214.28" fromTaz="631668821" toTaz="631668821">
        <routeDistribution last="0">
            <route cost="159.94" probability="1.00000000" edges="-49695726 49695726"/>
        </routeDistribution>
    </vehicle>
    <vehicle id="Flow21.5" type="Car21" depart="214.29" fromTaz="622618197" toTaz="622618015">
        <routeDistribution last="0">
            <route cost="0.21" probability="1.00000000" edges="593849721"/>
        </routeDistribution>
    </vehicle>
    <vehicle id="Flow17.14" type="Car17" depart="221.05" fromTaz="cluster_5372642442_631668976_631668981_631669076" toTaz="2690921409">
        <routeDistribution last="0">
            <route cost="101.20" probability="1.00000000" edges="506322851#0"/>
        </routeDistribution>
    </vehicle>
    <vehicle id="Flow0.3" type="Car0" depart="225.00" fromTaz="cluster_3431431575_4777363357_655375231_6982059025" toTaz="3196998953">
        <routeDistribution last="1">
            <route cost="474.88" probability="0.30141405" edges="51362429#0 1068440006#0 1334904386#0 303647015#0"/>
            <route cost="229.36" probability="0.39644904" edges="51362429#0 593847701 E0 -594658757#2 303647015#0"/>
            <route cost="459.23" probability="0.30213691" edges="51362429#0 1068440006#0 -594658757#2 303647015#0"/>
        </routeDistribution>
    </vehicle>
    <vehicle id="Flow1.3" type="Car1" depart="225.00" fromTaz="631668923" toTaz="622618112">
        <routeDistribution last="2">
            <route cost="296.22" probability="0.32063866" edges="1068234498#0 288135626#0 1068234499#0 -593847703#3 -593847705 593847704#0 49073272#0"/>
            <route cost="298.26" probability="0.33243271" edges="1068234498#0 288135626#0 1068234499#0 182334378#0 -E0 593847704#0 49073272#0"/>
            <route cost="367.66" probability="0.34692863" edges="1068234498#0 288135626#0 1068234499#0 -593847703#3 593847702#0"/>
        </routeDistribution>
    </vehicle>
    <vehicle id="Flow6.3" type="Car6" depart="225.00" fromTaz="6251747844" toTaz="cluster_5372642442_631668976_631668981_631669076">
        <routeDistribution last="0">
            <route cost="409.10" probability="1.00000000" edges="-260882327 -545977624#2 593842812#0 593842812#2 593844221#0 49695736#0 182334379#0"/>
        </routeDistribution>
    </vehicle>
    <vehicle id="Flow10.10" type="Car10" depart="230.76" fromTaz="cluster619136880_619136881_cluster_4510442270_5296993511_5296993513_619136931_#1more" toTaz="6252193077">
        <routeDistribution last="0">
            <route cost="281.60" probability="1.00000000" edges="196961377#0 196961377#3 593849718#0"/>
        </routeDistribution>
    </vehicle>
    <vehicle id="Flow12.10" type="Car12" depart="230.76" fromTaz="cluster_9383263990_9383263991_9383263992_9383263993" toTaz="cluster_9383263990_9383263991_9383263992_9383263993">
        <routeDistribution last="0">
            <route cost="52.39" probability="1.00000000" edges="506322841#1 182336886 30620492#1"/>
        </routeDistribution>
    </vehicle>
    <vehicle id="Flow15.10" type="Car15" depart="230.76" fromTaz="cluster619136880_619136881_cluster_4510442270_5296993511_5296993513_619136931_#1more" toTaz="622618165">
        <routeDistribution last="0">
            <route cost="132.70" probability="1.00000000" edges="48794887#0"/>
        </routeDistribution>
    </vehicle>
    <vehicle id="Flow4.7" type="Car4" depart="233.33" fromTaz="622618230" toTaz="2013717678">
        <routeDistribution last="2">
            <route cost="570.73" probability="0.28335716" edges="593849715 49073272#0 49073272#1 49073272#3 49073272#4 353392316#0 288135628#0"/>
            <route cost="477.98" probability="0.34675399" edges="593849711#0 593849711#2 593847701 593847705 593847703#0 182334379#0 288135628#0"/>
            <route cost="331.33" probability="0.36988885" edges="593849715 -593847704#2 593847705 593847703#0 182334379#0 288135628#0"/>
        </routeDistribution>
    </vehicle>
    <vehicle id="Flow7.11" type="Car7" depart="235.71" fromTaz="631668821" toTaz="631668821">
        <routeDistribution last="0">
            <route cost="179.48" probability="1.00000000" edges="-49695726 49695726"/>
        </routeDistribution>
    </vehicle>
    <vehicle id="Flow17.15" type="Car17" depart="236.84" fromTaz="cluster_5372642442_631668976_631668981_631669076" toTaz="2690921409">
        <routeDistribution last="0">
            <route cost="69.34" probability="1.00000000" edges="506322851#0"/>
        </routeDistribution>
    </vehicle>
    <vehicle id="Flow13.4" type="Car13" depart="240.00" fromTaz="622618015" toTaz="622618230">
        <routeDistribution last="0">
            <route cost="49.90" probability="1.00000000" edges="49073274 593852346"/>
        </routeDistribution>
    </vehicle>
    <vehicle id="Flow2.5" type="Car2" depart="250.00" fromTaz="cluster655375228_655375240" toTaz="3208478132">
        <routeDistribution last="1">
            <route cost="385.19" probability="0.44032375" edges="-E1 263217604#0 360843888 244450512#4 314800955"/>
            <route cost="281.88" probability="0.55967625" edges="-E1 -300077497#8 -300077497#5 182334378#0 232003903#0 51289045#1"/>
        </routeDistribution>
    </vehicle>
    <vehicle id="Flow5.5" type="Car5" depart="250.00" fromTaz="7782558678" toTaz="3431431576">
        <routeDistribution last="1">
            <route cost="158.85" probability="0.54595734" edges="196961215#0 196961215#2 241518668#0 336063376#0"/>
            <route cost="198.23" probability="0.45404266" edges="196961215#0 196961215#2 288878926#0 593849711#0"/>
        </routeDistribution>
    </vehicle>
    <vehicle id="Flow17.16" type="Car17" depart="252.62" fromTaz="cluster_5372642442_631668976_631668981_631669076" toTaz="2690921409">
        <routeDistribution last="0">
            <route cost="27.33" probability="1.00000000" edges="506322851#0"/>
        </routeDistribution>
    </vehicle>
    <vehicle id="Flow10.11" type="Car10" depart="253.84" fromTaz="cluster619136880_619136881_cluster_4510442270_5296993511_5296993513_619136931_#1more" toTaz="6252193077">
        <routeDistribution last="0">
            <route cost="327.70" probability="1.00000000" edges="196961377#0 196961377#3 593849718#0"/>
        </routeDistribution>
    </vehicle>
    <vehicle id="Flow12.11" type="Car12" depart="253.84" fromTaz="cluster_9383263990_9383263991_9383263992_9383263993" toTaz="cluster_9383263990_9383263991_9383263992_9383263993">
        <routeDistribution last="0">
            <route cost="63.22" probability="1.00000000" edges="506322841#1 182336886 30620492#1"/>
        </routeDistribution>
    </vehicle>
    <vehicle id="Flow15.11" type="Car15" depart="253.84" fromTaz="cluster619136880_619136881_cluster_4510442270_5296993511_5296993513_619136931_#1more" toTaz="622618165">
        <routeDistribution last="0">
            <route cost="172.18" probability="1.00000000" edges="48794887#0"/>
        </routeDistribution>
    </vehicle>
    <vehicle id="Flow7.12" type="Car7" depart="257.14" fromTaz="631668821" toTaz="631668821">
        <routeDistribution last="0">
            <route cost="165.07" probability="1.00000000" edges="-49695726 49695726"/>
        </routeDistribution>
    </vehicle>
    <vehicle id="Flow21.6" type="Car21" depart="257.14" fromTaz="622618197" toTaz="622618015">
        <routeDistribution last="0">
            <route cost="0.12" probability="1.00000000" edges="593849721"/>
        </routeDistribution>
    </vehicle>
    <vehicle id="Flow4.8" type="Car4" depart="266.66" fromTaz="622618230" toTaz="2013717678">
        <routeDistribution last="1">
            <route cost="352.44" probability="0.35058223" edges="593849711#0 593849711#2 593847701 593847705 593847703#0 182334379#0 288135628#0"/>
            <route cost="460.03" probability="0.33990395" edges="593849715 49073272#0 49073272#1 49073272#3 49073272#4 353392316#0 288135628#0"/>
            <route cost="448.41" probability="0.30951382" edges="593849715 -593847704#2 593847705 593847703#0 182334379#0 288135628#0"/>
        </routeDistribution>
    </vehicle>
    <vehicle id="Flow17.17" type="Car17" depart="268.41" fromTaz="cluster_5372642442_631668976_631668981_631669076" toTaz="2690921409">
        <routeDistribution last="0">
            <route cost="135.62" probability="1.00000000" edges="506322851#0"/>
        </routeDistribution>
    </vehicle>
    <vehicle id="Flow10.12" type="Car10" depart="276.91" fromTaz="cluster619136880_619136881_cluster_4510442270_5296993511_5296993513_619136931_#1more" toTaz="6252193077">
        <routeDistribution last="0">
            <route cost="216.46" probability="1.00000000" edges="196961377#0 196961377#3 593849718#0"/>
        </routeDistribution>
    </vehicle>
    <vehicle id="Flow12.12" type="Car12" depart="276.91" fromTaz="cluster_9383263990_9383263991_9383263992_9383263993" toTaz="cluster_9383263990_9383263991_9383263992_9383263993">
        <routeDistribution last="1">
            <route cost="62.72" probability="0.54361336" edges="506322841#1 182336886 30620492#1"/>
            <route cost="81.38" probability="0.45638664" edges="506322840#0 -1334905223#2 263217603#0"/>
        </routeDistribution>
    </vehicle>
    <vehicle id="Flow15.12" type="Car15" depart="276.91" fromTaz="cluster619136880_619136881_cluster_4510442270_5296993511_5296993513_619136931_#1more" toTaz="622618165">
        <routeDistribution last="0">
            <route cost="128.73" probability="1.00000000" edges="48794887#0"/>
        </routeDistribution>
    </vehicle>
    <vehicle id="Flow7.13" type="Car7" depart="278.56" fromTaz="631668821" toTaz="631668821">
        <routeDistribution last="0">
            <route cost="170.91" probability="1.00000000" edges="-49695726 49695726"/>
        </routeDistribution>
    </vehicle>
    <vehicle id="Flow17.18" type="Car17" depart="284.20" fromTaz="cluster_5372642442_631668976_631668981_631669076" toTaz="2690921409">
        <routeDistribution last="0">
            <route cost="68.41" probability="1.00000000" edges="506322851#0"/>
        </routeDistribution>
    </vehicle>
</routes>
